Metadata-Version: 2.1
Name: pySCM
Version: 0.2.1
Summary: A basic simple climate model in Python
Home-page: http://pythonhosted.org/pySCM
Author: Jared Lewis
Author-email: jared@bodekerscientific.com
License: MIT
Project-URL: Bug Reports, https://github.com/bodekerscientific/pyscm/issues
Project-URL: Source, https://github.com/bodekerscientific/pyscm/
Keywords: simple climate model SCM climate science
Platform: UNKNOWN
Classifier: Development Status :: 3 - Alpha
Classifier: Topic :: Scientific/Engineering
Classifier: License :: OSI Approved :: MIT License
Classifier: Intended Audience :: Science/Research
Classifier: Programming Language :: Python :: 3
Classifier: Programming Language :: Python :: 3.5
Classifier: Programming Language :: Python :: 3.6
Provides-Extra: dev
Provides-Extra: docs
